[
  {
    "tokenSymbol": "PEM",
    "apy": [
      5.3
    ],
    "chainName": "Near",
    "protocol": "Pembrock"
  },
  {
    "tokenSymbol": "wNEAR",
    "apy": [
      10.05
    ],
    "chainName": "Near",
    "protocol": "Pembrock"
  },
  {
    "tokenSymbol": "STNEAR",
    "apy": [
      13.46
    ],
    "chainName": "Near",
    "protocol": "Pembrock"
  },
  {
    "tokenSymbol": "LINEAR",
    "apy": [
      3.69
    ],
    "chainName": "Near",
    "protocol": "Pembrock"
  },
  {
    "tokenSymbol": "NearX",
    "apy": [
      12.31
    ],
    "chainName": "Near",
    "protocol": "Pembrock"
  },
  {
    "tokenSymbol": "REF",
    "apy": [
      4.66
    ],
    "chainName": "Near",
    "protocol": "Pembrock"
  },
  {
    "tokenSymbol": "USDT.e",
    "apy": [
      7.29
    ],
    "chainName": "Near",
    "protocol": "Pembrock"
  },
  {
    "tokenSymbol": "USDC.e",
    "apy": [
      10.79
    ],
    "chainName": "Near",
    "protocol": "Pembrock"
  },
  {
    "tokenSymbol": "SWEAT",
    "apy": [
      18.78
    ],
    "chainName": "Near",
    "protocol": "Pembrock"
  },
  {
    "tokenSymbol": "ETH",
    "apy": [
      5.58
    ],
    "chainName": "Near",
    "protocol": "Pembrock"
  },
  {
    "tokenSymbol": "WBTC",
    "apy": [
      8.24
    ],
    "chainName": "Near",
    "protocol": "Pembrock"
  },
  {
    "tokenSymbol": "USN",
    "apy": [
      0
    ],
    "chainName": "Near",
    "protocol": "Pembrock"
  }
]