[
  {
    "tokenSymbol": "PEM",
    "apy": [
      5.07
    ],
    "chainName": "Near",
    "protocol": "Pembrock"
  },
  {
    "tokenSymbol": "wNEAR",
    "apy": [
      122.24
    ],
    "chainName": "Near",
    "protocol": "Pembrock"
  },
  {
    "tokenSymbol": "STNEAR",
    "apy": [
      12.22
    ],
    "chainName": "Near",
    "protocol": "Pembrock"
  },
  {
    "tokenSymbol": "LINEAR",
    "apy": [
      3.81
    ],
    "chainName": "Near",
    "protocol": "Pembrock"
  },
  {
    "tokenSymbol": "NearX",
    "apy": [
      10.28
    ],
    "chainName": "Near",
    "protocol": "Pembrock"
  },
  {
    "tokenSymbol": "REF",
    "apy": [
      4.85
    ],
    "chainName": "Near",
    "protocol": "Pembrock"
  },
  {
    "tokenSymbol": "USDT.e",
    "apy": [
      7.47
    ],
    "chainName": "Near",
    "protocol": "Pembrock"
  },
  {
    "tokenSymbol": "USDC.e",
    "apy": [
      10.87
    ],
    "chainName": "Near",
    "protocol": "Pembrock"
  },
  {
    "tokenSymbol": "SWEAT",
    "apy": [
      18.68
    ],
    "chainName": "Near",
    "protocol": "Pembrock"
  },
  {
    "tokenSymbol": "ETH",
    "apy": [
      8.18
    ],
    "chainName": "Near",
    "protocol": "Pembrock"
  },
  {
    "tokenSymbol": "WBTC",
    "apy": [
      7.05
    ],
    "chainName": "Near",
    "protocol": "Pembrock"
  },
  {
    "tokenSymbol": "USN",
    "apy": [
      0
    ],
    "chainName": "Near",
    "protocol": "Pembrock"
  }
]